Metadata-Version: 1.0
Name: zuby-test-dsnd-distributions
Version: 0.1
Summary: Gaussian and Binomial distributions
Home-page: UNKNOWN
Author: Zubair Abubakar
Author-email: zuby52@gmail.com
License: UNKNOWN
Platform: UNKNOWN
